contador/contador_hex.v
// Contador Hexadecimal de 0 a F
module contador_hex (
    input clk,            // Clock
    input rst_n,          // Reset Assíncrono, ATIVO BAIXO (rst_n de 'not')
    input dir,      // 0: Contagem incremental; 1: Contagem decremental
    
    output reg [3:0] q    // Saída do Contador (4 bits)
);
   // O registrador de contagem já está implícito em 'q' (reg)

   // Lógica do Contador (Reset Assíncrono, Ativo Baixo)
    always @(posedge clk, negedge rst_n) begin
        
        if (rst_n == 1'b0) begin
            // Reset: zera o contador
            q <= 4'b0000;
        end 
        else begin // Síncrono com CLK
            
            if (dir == 1'b1) begin
                // Decrementar (Contagem para baixo) - Cicla de 0 para F
                q <= q - 1;
            end 
            
            else begin
                // Incrementar (Contagem para cima)
                if (q == 4'hF) begin
                    // Se q é F, mantém o valor (Parada)
                    q <= q; 
                end else begin
                    // Contagem normal (0 -> F)
                    q <= q + 1;
                end
            end
        end
    end

endmodule

contador/contador_hex_tb.v
// Testbench para o Contador Up/Down com teste de Parada em F e Reset
`include "contador_hex.v" 
`timescale 1ns/1ns

module contador_hex_tb;

    // Sinais 
    reg clk;
    reg rst_n;          // Reset Ativo Baixo
    reg dir;      // 0: UP
    wire [3:0] q;

    // Instanciação do DUT (Device Under Test)
    contador_hex DUT (
        .clk (clk),
        .rst_n (rst_n),      
        .dir (dir),
        .q (q)
    );

    // Geração do Clock (Período de 200ns)
    initial begin
        clk = 1'b0;
        forever #100 clk = ~clk; 
    end

    // Geração do Estímulo
    initial begin
        $dumpfile("contador_hex.vcd");
        $dumpvars(0, contador_hex_tb);
        
        // --- 1. RESET INICIAL (Zera para sair do estado 'x') ---
        rst_n = 1'b0; // Reset Ativo Baixo
        dir = 1'b0; // Contagem UP
        #50; 
        rst_n = 1'b1; // Desativa o Reset
        
        // --- 2. CONTAGEM ATÉ F E PARADA ---
        // 16 ciclos (15*200ns + 100ns de margem) = 3100 ns
        // Garante que ele chegue em F e tente incrementar
        #3100; 
        
        #800; // Mantém em F por 4 ciclos de clock

        // --- 3. APLICAÇÃO DO RESET MANUAL ---
        rst_n = 1'b0; // Ativa Reset (Deve zerar o contador imediatamente)
        #50; 
        rst_n = 1'b1; // Desativa o Reset
        
        // --- 4. VERIFICAÇÃO DO REINÍCIO (0, 1, 2) ---
        #600; // 3 ciclos de contagem (deve ir 0, 1, 2)
        dir = 1'b1; // Contagem DOWN
         #600;
        $finish; 
    end

    // Monitoramento
    initial $monitor("Tempo=%4d | RST_n=%b | Dir=%b | Q=%h", $time, rst_n, dir, q);

endmodule

contador/contador_hex.vcd
$date
	Sat Dec 13 18:15:30 2025
$end
$version
	Icarus Verilog
$end
$timescale
	1ns
$end
$scope module contador_hex_tb $end
$var wire 4 ! q [3:0] $end
$var reg 1 " clk $end
$var reg 1 # dir $end
$var reg 1 $ rst_n $end
$scope module DUT $end
$var wire 1 " clk $end
$var wire 1 # dir $end
$var wire 1 $ rst_n $end
$var reg 4 % q [3:0] $end
$upscope $end
$upscope $end
$enddefinitions $end
$comment Show the parameter values. $end
$dumpall
$end
#0
$dumpvars
b0 %
0$
0#
0"
b0 !
$end
#50
1$
#100
b1 !
b1 %
1"
#200
0"
#300
b10 !
b10 %
1"
#400
0"
#500
b11 !
b11 %
1"
#600
0"
#700
b100 !
b100 %
1"
#800
0"
#900
b101 !
b101 %
1"
#1000
0"
#1100
b110 !
b110 %
1"
#1200
0"
#1300
b111 !
b111 %
1"
#1400
0"
#1500
b1000 !
b1000 %
1"
#1600
0"
#1700
b1001 !
b1001 %
1"
#1800
0"
#1900
b1010 !
b1010 %
1"
#2000
0"
#2100
b1011 !
b1011 %
1"
#2200
0"
#2300
b1100 !
b1100 %
1"
#2400
0"
#2500
b1101 !
b1101 %
1"
#2600
0"
#2700
b1110 !
b1110 %
1"
#2800
0"
#2900
b1111 !
b1111 %
1"
#3000
0"
#3100
1"
#3200
0"
#3300
1"
#3400
0"
#3500
1"
#3600
0"
#3700
1"
#3800
0"
#3900
1"
#3950
b0 !
b0 %
0$
#4000
1$
0"
#4100
b1 !
b1 %
1"
#4200
0"
#4300
b10 !
b10 %
1"
#4400
0"
#4500
b11 !
b11 %
1"
#4600
0"
1#
#4700
b10 !
b10 %
1"
#4800
0"
#4900
b1 !
b1 %
1"
#5000
0"
#5100
b0 !
b0 %
1"
